README.md
pyproject.toml
src/lctime/__init__.py
src/lctime/cell_types.py
src/lctime/licence.py
src/lctime.egg-info/PKG-INFO
src/lctime.egg-info/SOURCES.txt
src/lctime.egg-info/dependency_links.txt
src/lctime.egg-info/entry_points.txt
src/lctime.egg-info/requires.txt
src/lctime.egg-info/top_level.txt
src/lctime/characterization/__init__.py
src/lctime/characterization/flatten.py
src/lctime/characterization/flipflop.py
src/lctime/characterization/input_capacitance.py
src/lctime/characterization/leakage_power.py
src/lctime/characterization/main_lctime.py
src/lctime/characterization/main_sp2bool.py
src/lctime/characterization/ngspice_subprocess.py
src/lctime/characterization/piece_wise_linear.py
src/lctime/characterization/test_ngspice_shared.py
src/lctime/characterization/test_ngspice_subprocess.py
src/lctime/characterization/timing_combinatorial.py
src/lctime/characterization/timing_sequential.py
src/lctime/characterization/util.py
src/lctime/lccommon/__init__.py
src/lctime/lccommon/data_types.py
src/lctime/lccommon/net_util.py
src/lctime/lccommon/spice_parser.py
src/lctime/liberty/__init__.py
src/lctime/liberty/merge.py
src/lctime/liberty/util.py
src/lctime/liberty/visualize.py
src/lctime/logic/__init__.py
src/lctime/logic/cmos_sim.py
src/lctime/logic/cmos_synth.py
src/lctime/logic/functional_abstraction.py
src/lctime/logic/graph_enumeration.py
src/lctime/logic/seq_recognition.py
src/lctime/logic/types.py
src/lctime/logic/util.py
src/lctime/transistor_sizing/__init__.py
src/lctime/transistor_sizing/width_opt.py