Metadata-Version: 2.4
Name: lctime
Version: 0.0.26
Summary: CMOS standard-cell characterization kit.
Author-email: "T. Kramer" <code@tkramer.ch>
License: AGPL-3.0-or-later
Project-URL: Homepage, https://codeberg.org/librecell/lctime
Project-URL: Repository, https://codeberg.org/librecell/lctime
Project-URL: Issue Tracker, https://codeberg.org/librecell/lctime/issues
Keywords: cmos,cell,characterization,vlsi,asic
Classifier: License :: OSI Approved :: GNU Affero General Public License v3 or later (AGPLv3+)
Classifier: Development Status :: 3 - Alpha
Classifier: Topic :: Scientific/Engineering
Classifier: Topic :: Scientific/Engineering :: Electronic Design Automation (EDA)
Classifier: Programming Language :: Python :: 3
Requires-Python: >=3.7
Requires-Dist: klayout>=0.29.0
Requires-Dist: numpy>=1.0
Requires-Dist: sympy>=1.6
Requires-Dist: matplotlib>=3.0
Requires-Dist: networkx>=2.5
Requires-Dist: pyspice>=1.4
Requires-Dist: scipy>=1.5
Requires-Dist: liberty-parser>=0.0.23
Requires-Dist: joblib>=0.14
